xtralien/__init__.py
xtralien/__main__.py
xtralien/discover.py
xtralien/experiment.py
xtralien/imports.py
xtralien/mixins.py
xtralien/prompt.py
xtralien/serial_utils.py
xtralien/smartboard.py
xtralien/compat/__init__.py
xtralien/compat/__main__.py
xtralien/compat/keithley.py
xtralien/compat/minolta.py
xtralien-2.11.2.dist-info/licenses/LICENSE
xtralien-2.11.2.dist-info/METADATA
xtralien-2.11.2.dist-info/WHEEL
xtralien-2.11.2.dist-info/top_level.txt
xtralien-2.11.2.dist-info/RECORD
