Metadata-Version: 2.4
Name: xtralien
Version: 2.11.2
Summary: A library for controlling Ossila's Source Measure Unit
Home-page: https://github.com/xtralien/pyxtralien.git
Author: Ossila Ltd.
Author-email: info@ossila.com
License: MIT
Requires-Python: >=3.5
License-File: LICENSE
Provides-Extra: numpy
Requires-Dist: numpy; extra == "numpy"
Provides-Extra: serial
Requires-Dist: pyserial; extra == "serial"
Provides-Extra: keithley
Requires-Dist: pyVISA; extra == "keithley"
Provides-Extra: prompt
Requires-Dist: pyreadline; extra == "prompt"
Dynamic: author
Dynamic: author-email
Dynamic: description
Dynamic: description-content-type
Dynamic: home-page
Dynamic: license
Dynamic: license-file
Dynamic: provides-extra
Dynamic: requires-python
Dynamic: summary
